MANIFEST.in
README.md
setup.cfg
setup.py
filebrowser_s3/__init__.py
filebrowser_s3/storage.py
filebrowser_s3.egg-info/PKG-INFO
filebrowser_s3.egg-info/SOURCES.txt
filebrowser_s3.egg-info/dependency_links.txt
filebrowser_s3.egg-info/not-zip-safe
filebrowser_s3.egg-info/top_level.txt
filebrowser_s3/templates/filebrowser/include/filelisting.html
filebrowser_s3/templatetags/__init__.py
filebrowser_s3/templatetags/s3thumbnails.py