Metadata-Version: 1.1
Name: filebrowser-s3
Version: 1.0.0
Summary: An S3 fix for Mezzanine's media manager.
Home-page: https://github.com/Pomax/filebrowser_s3
Author: Pomax
Author-email: pomax@mozillafoundation.org
License: UNKNOWN
Download-URL: https://github.com/Pomax/filebrowser_s3/archive/1.0.0.tar.gz
Platform: UNKNOWN
